{
  "project_info": {
    "project_number": "678043215630",
    "project_id": "noticeboard-25caa",
    "storage_bucket": "noticeboard-25caa.firebasestorage.app"
  },
  "client": [
    {
      "client_info": {
        "mobilesdk_app_id": "1:678043215630:android:6d161fbd22f26b8b92595f",
        "android_client_info": {
          "package_name": "com.example.noticeboard"
        }
      },
      "oauth_client": [],
      "api_key": [
        {
          "current_key": "AIzaSyBnhrx0BiyqOWXz-V40DSgyCa8UtWsXlVM"
        }
      ],
      "services": {
        "appinvite_service": {
          "other_platform_oauth_client": []
        }
      }
    }
  ],
  "configuration_version": "1"
}